{
"type": "FeatureCollection",
"name": "basecampPoint",
"crs": { "type": "name", "properties": { "name": "urn:ogc:def:crs:OGC:1.3:CRS84" } },
"features": [
{ "type": "Feature", "properties": { "Name": "BaseCamp", "descriptio": "BaseCamp", "timestamp": null, "begin": null, "end": null, "altitudeMo": null, "tessellate": null, "extrude": null, "visibility": null, "drawOrder": null, "icon": null }, "geometry": { "type": "Point", "coordinates": [ -78.806785265522123, 0.319541305083173 ] } }
]
}
