{
"type": "FeatureCollection",
"name": "LodgePoint",
"crs": { "type": "name", "properties": { "name": "urn:ogc:def:crs:OGC:1.3:CRS84" } },
"features": [
{ "type": "Feature", "properties": { "Name": "Lodge", "descriptio": "Lodge", "timestamp": null, "begin": null, "end": null, "altitudeMo": null, "tessellate": -1, "extrude": 0, "visibility": -1, "drawOrder": null, "icon": null }, "geometry": { "type": "Point", "coordinates": [ -78.779384708273383, 0.30885233176121 ] } },
{ "type": "Feature", "properties": { "Name": "Chontal", "descriptio": "Chontal", "timestamp": null, "begin": null, "end": null, "altitudeMo": null, "tessellate": -1, "extrude": 0, "visibility": -1, "drawOrder": null, "icon": null }, "geometry": { "type": "Point", "coordinates": [ -78.745865243626127, 0.233470834610886 ] } }
]
}
